decoded_sdk/__init__.py
decoded_sdk-0.1.0.dist-info/METADATA
decoded_sdk-0.1.0.dist-info/WHEEL
decoded_sdk-0.1.0.dist-info/RECORD
