Metadata-Version: 2.3
Name: decoded-sdk
Version: 0.1.0
Summary: 
Author: CIOI
Author-email: rhkr9693@gmail.com
Requires-Python: >=3.11
Classifier: Programming Language :: Python :: 3
Classifier: Programming Language :: Python :: 3.11
Classifier: Programming Language :: Python :: 3.12
Classifier: Programming Language :: Python :: 3.13
Requires-Dist: typesense (>=1.1.1,<2.0.0)
